.gitignore
Dockerfile
LICENSE.txt
MANIFEST
MANIFEST.in
README.md
dmx-head.png
setup.cfg
setup.py
test.py
face_replace/__init__.py
face_replace/face.py
face_replace/face_types.py
face_replace/finder.py
face_replace/replacer.py
face_replace.egg-info/PKG-INFO
face_replace.egg-info/SOURCES.txt
face_replace.egg-info/dependency_links.txt
face_replace.egg-info/requires.txt
face_replace.egg-info/top_level.txt