Metadata-Version: 1.1
Name: face-replace
Version: 0.1.8
Summary: Simple facial recognition and face replacement
Home-page: https://github.com/mattmatters/face_replace
Author: Matt Lewis
Author-email: domattthings@gmail.com
License: MIT
Download-URL: https://github.com/mattmatters/face_replace/archive/0.1.8.tar.gz
Platform: UNKNOWN
